KinMS/KinMS_core.py
KinMS/KinMS_testsuite.py
KinMS/__init__.py
KinMS/utils/KinMS_figures.py
KinMS/utils/__init__.py
KinMS/utils/sauron_colormap.py
kinmspytest-2.0.10.dist-info/LICENSE
kinmspytest-2.0.10.dist-info/METADATA
kinmspytest-2.0.10.dist-info/WHEEL
kinmspytest-2.0.10.dist-info/top_level.txt
kinmspytest-2.0.10.dist-info/RECORD
