Metadata-Version: 2.1
Name: kinmspytest
Version: 2.0.10
Summary: Kinematic molecular simulation tool for astronomers
Home-page: https://github.com/TimothyADavis/KinMSpy/tree/dev
Author: KinMS_Team
Author-email: dawsonj5@cardiff.ac.uk
License: UNKNOWN
Platform: UNKNOWN
Classifier: Programming Language :: Python :: 3
Classifier: License :: OSI Approved :: MIT License
Classifier: Operating System :: OS Independent
Requires-Python: >=3.5
